esp-stubs/__init__.pyi
esp-stubs/sub_pkg/__init__.pyi
esp32-stubs/__init__.pyi
esp32-stubs/sub_pkg.pyi
machine.pyi
upip.pyi
uuid-stubs/__init__.pyi
uuid-stubs/py.typed
esp32_test_stubs-0.1.2.dist-info/WHEEL
esp32_test_stubs-0.1.2.dist-info/METADATA
esp32_test_stubs-0.1.2.dist-info/RECORD
