Metadata-Version: 2.1
Name: esp32-test-stubs
Version: 0.1.2
Summary: Sample project for PEP-561 distribution testing
Home-page: https://github.com/mrkeuz/esp32-test-stubs
License: MIT
Author: mrkeuz
Author-email: mrkeuz@users.noreply.github.com
Requires-Python: >=3.8,<4.0
Classifier: Development Status :: 3 - Alpha
Classifier: License :: OSI Approved :: MIT License
Classifier: Programming Language :: Python
Classifier: Programming Language :: Python :: 3
Classifier: Programming Language :: Python :: 3 :: Only
Classifier: Programming Language :: Python :: 3.8
Classifier: Programming Language :: Python :: 3.9
